kerfed_api/__init__.py
kerfed_api/order.py
kerfed_api/quote.py
kerfed_api/shop.py
kerfed_api/version.py
kerfed_api-0.0.2.dist-info/LICENSE
kerfed_api-0.0.2.dist-info/METADATA
kerfed_api-0.0.2.dist-info/WHEEL
kerfed_api-0.0.2.dist-info/top_level.txt
kerfed_api-0.0.2.dist-info/RECORD
