Metadata-Version: 2.1
Name: kerfed-api
Version: 0.0.2
Summary: Analyze CAD assemblies using the Kerfed API.
Home-page: https://github.com/kerfed/kerfed-api-python
Author: Kerfed Intelligent Manufacturing
Author-email: api@kerfed.com
License: MIT
Keywords: CAD solidworks geometry quoting manufacturing
Platform: UNKNOWN
Classifier: Development Status :: 4 - Beta
Classifier: License :: OSI Approved :: MIT License
Classifier: Programming Language :: Python
Classifier: Programming Language :: Python :: 2.7
Classifier: Programming Language :: Python :: 3.5
Classifier: Programming Language :: Python :: 3.6
Classifier: Programming Language :: Python :: 3.7
Classifier: Programming Language :: Python :: 3.9
Classifier: Programming Language :: Python :: 3.8
Classifier: Natural Language :: English
Classifier: Topic :: Scientific/Engineering
Requires-Dist: requests
Provides-Extra: all
Requires-Dist: trimesh[easy] ; extra == 'all'
Requires-Dist: pandas ; extra == 'all'
Requires-Dist: openpyxl ; extra == 'all'
Requires-Dist: webcolors ; extra == 'all'
